threatminer/__init__.py
threatminer/threatminer.py
threatminer-1.0.dist-info/DESCRIPTION.rst
threatminer-1.0.dist-info/METADATA
threatminer-1.0.dist-info/RECORD
threatminer-1.0.dist-info/WHEEL
threatminer-1.0.dist-info/metadata.json
threatminer-1.0.dist-info/top_level.txt
