Metadata-Version: 2.0
Name: threatminer
Version: 1.0
Summary: Library to interface with ThreatMiner's API
Home-page: https://github.com/asrabon/ThreatMiner
Author: Sloan Rabon
Author-email: sloanrabon@gmail.com
License: GNU General Public License v3.0
Platform: UNKNOWN
Requires-Dist: requests
Requires-Dist: urllib3
